docs/faq.md
docs/index.md
docs/tags.md
docs/api/index.md
docs/assets/animations/ebm_training_animation.gif
docs/assets/images/energy_grid_bg.png
docs/assets/images/favicon.svg
docs/assets/images/logo_with_text.svg
docs/assets/images/nabla_icon.svg
docs/assets/images/parallel.jpg
docs/assets/images/sampling.jpg
docs/assets/images/trajectory.jpg
docs/assets/images/blog/hamiltonian/non-L-pendulum.png
docs/assets/images/blog/hamiltonian/numerical_err.png
docs/assets/images/blog/hamiltonian/pendulum_phase_space.mp4
docs/assets/images/blog/hamiltonian/quadratics.png
docs/assets/images/datasets/checkerboard.png
docs/assets/images/datasets/circle.png
docs/assets/images/datasets/eight_gaussians.png
docs/assets/images/datasets/gaussian_mixture.png
docs/assets/images/datasets/grid.png
docs/assets/images/datasets/pinwheel.png
docs/assets/images/datasets/swiss_roll.png
docs/assets/images/datasets/two_moons.png
docs/assets/images/e_functions/ackley.png
docs/assets/images/e_functions/double_well.png
docs/assets/images/e_functions/gaussian.png
docs/assets/images/e_functions/harmonic.png
docs/assets/images/e_functions/rastrigin.png
docs/assets/images/e_functions/rosenbrock.png
docs/assets/images/examples/double_well_trajectory.png
docs/assets/images/examples/energy_landscape_epoch_10.png
docs/assets/images/examples/energy_landscape_epoch_100.png
docs/assets/images/examples/energy_landscape_epoch_20.png
docs/assets/images/examples/energy_landscape_epoch_30.png
docs/assets/images/examples/energy_landscape_epoch_40.png
docs/assets/images/examples/energy_landscape_epoch_50.png
docs/assets/images/examples/energy_landscape_epoch_60.png
docs/assets/images/examples/energy_landscape_epoch_70.png
docs/assets/images/examples/energy_landscape_epoch_80.png
docs/assets/images/examples/energy_landscape_epoch_90.png
docs/assets/images/examples/energy_landscape_final.png
docs/assets/images/examples/gaussian_mixture_target.png
docs/assets/images/examples/hmc_basic.png
torchebm-0.5.1.dist-info/licenses/LICENSE
torchebm-0.5.1.dist-info/METADATA
torchebm-0.5.1.dist-info/WHEEL
torchebm-0.5.1.dist-info/top_level.txt
torchebm-0.5.1.dist-info/RECORD
