Metadata-Version: 2.4
Name: torchebm
Version: 0.5.1
Summary: Components and algorithms for energy-based models
Author-email: Soran Ghaderi <soran.gdr.cs@gmail.com>
License: MIT License
Project-URL: homepage, https://github.com/soran-ghaderi/torchebm
Project-URL: documentation, https://soran-ghaderi.github.io/torchebm/
Project-URL: repository, https://github.com/soran-ghaderi/torchebm.git
Project-URL: changelog, https://github.com/soran-ghaderi/torchebm/blob/main/CHANGELOG.md
Keywords: deep-learning,energy-based-models,pytorch
Classifier: Development Status :: 3 - Alpha
Classifier: Intended Audience :: Developers
Classifier: Intended Audience :: Science/Research
Classifier: License :: OSI Approved :: MIT License
Classifier: Programming Language :: Python :: 3
Classifier: Programming Language :: Python :: 3.9
Classifier: Programming Language :: Python :: 3.10
Classifier: Programming Language :: Python :: 3.11
Classifier: Programming Language :: Python :: 3.12
Classifier: Programming Language :: Python :: 3.13
Classifier: Topic :: Scientific/Engineering :: Artificial Intelligence
Classifier: Topic :: Scientific/Engineering :: Physics
Classifier: Topic :: Software Development :: Libraries :: Python Modules
Classifier: Topic :: Software Development :: Libraries
Classifier: Operating System :: OS Independent
License-File: LICENSE
Requires-Dist: torch
Requires-Dist: numpy
Requires-Dist: matplotlib
Provides-Extra: dev
Requires-Dist: pytest>=6.0; extra == "dev"
Requires-Dist: pytest-cov>=2.0; extra == "dev"
Requires-Dist: mypy>=0.800; extra == "dev"
Requires-Dist: black>=20.8b1; extra == "dev"
Requires-Dist: isort>=5.0; extra == "dev"
Provides-Extra: eqm
Requires-Dist: timm>=0.9.0; extra == "eqm"
Requires-Dist: torchvision; extra == "eqm"
Requires-Dist: torchdiffeq>=0.2.3; extra == "eqm"
Requires-Dist: diffusers>=0.25.0; extra == "eqm"
Requires-Dist: transformers>=4.35.0; extra == "eqm"
Requires-Dist: accelerate>=0.25.0; extra == "eqm"
Requires-Dist: safetensors>=0.4.0; extra == "eqm"
Provides-Extra: docs
Requires-Dist: mkdocs-material>=9.0.0; extra == "docs"
Requires-Dist: mkdocstrings[python]>=0.18; extra == "docs"
Requires-Dist: mike>=1.0.0; extra == "docs"
Requires-Dist: tomli>=2.0.0; extra == "docs"
Requires-Dist: pyyaml>=6.0; extra == "docs"
Requires-Dist: mkdocs-git-revision-date-localized-plugin>=1.0.0; extra == "docs"
Requires-Dist: mkdocs-glightbox>=0.3.0; extra == "docs"
Requires-Dist: mkdocs-blog-plugin>=0.1.0; extra == "docs"
Requires-Dist: mkdocs-gen-files>=0.4.0; extra == "docs"
Requires-Dist: mkdocs-literate-nav>=0.4.0; extra == "docs"
Requires-Dist: mkdocs-section-index>=0.3.0; extra == "docs"
Requires-Dist: pymdown-extensions>=9.0; extra == "docs"
Requires-Dist: mkdocs-autorefs; extra == "docs"
Requires-Dist: mkdocs-minify-plugin>=0.3.0; extra == "docs"
Requires-Dist: Pillow>=9.0.0; extra == "docs"
Dynamic: license-file
